{
  "localRoots": [
    {
      "accessPoints": [
        {
          "address": "host.docker.internal",
          "port": 3030
        },
        {
          "address": "host.docker.internal",
          "port": 3028
        },
        {
          "address": "host.docker.internal",
          "port": 3004
        },
        {
          "address": "host.docker.internal",
          "port": 3009
        }
      ],
      "advertise": true,
      "valency": 3
    }
  ],
  "publicRoots": [],
  "useLedgerAfterSlot": 0
}
